{"frames": {"a1358004": {"frame": {"x": 1107, "y": 1550, "w": 213, "h": 256}, "spriteSourceSize": {"x": 0, "y": 0, "w": 256, "h": 213}, "sourceSize": {"w": 256, "h": 213}, "rotated": true, "offset": {"x": 0, "y": 0}}, "a1358008": {"frame": {"x": 2058, "y": 3098, "w": 203, "h": 256}, "spriteSourceSize": {"x": 0, "y": 0, "w": 256, "h": 203}, "sourceSize": {"w": 256, "h": 203}, "rotated": true, "offset": {"x": 0, "y": 0}}, "a1358015": {"frame": {"x": 2617, "y": 2840, "w": 216, "h": 256}, "spriteSourceSize": {"x": 0, "y": 0, "w": 256, "h": 216}, "sourceSize": {"w": 256, "h": 216}, "rotated": true, "offset": {"x": 0, "y": 0}}, "a1358019": {"frame": {"x": 1500, "y": 1292, "w": 204, "h": 256}, "spriteSourceSize": {"x": 0, "y": 0, "w": 256, "h": 204}, "sourceSize": {"w": 256, "h": 204}, "rotated": true, "offset": {"x": 0, "y": 0}}, "a1358022": {"frame": {"x": 3167, "y": 518, "w": 217, "h": 256}, "spriteSourceSize": {"x": 0, "y": 0, "w": 256, "h": 217}, "sourceSize": {"w": 256, "h": 217}, "rotated": true, "offset": {"x": 0, "y": 0}}, "a1358031": {"frame": {"x": 1683, "y": 3356, "w": 212, "h": 256}, "spriteSourceSize": {"x": 0, "y": 0, "w": 256, "h": 212}, "sourceSize": {"w": 256, "h": 212}, "rotated": true, "offset": {"x": 0, "y": 0}}, "a1358034": {"frame": {"x": 3862, "y": 389, "w": 231, "h": 256}, "spriteSourceSize": {"x": 0, "y": 0, "w": 256, "h": 231}, "sourceSize": {"w": 256, "h": 231}, "rotated": true, "offset": {"x": 0, "y": 0}}, "a1358035": {"frame": {"x": 260, "y": 3872, "w": 256, "h": 222}, "spriteSourceSize": {"x": 0, "y": 0, "w": 256, "h": 222}, "sourceSize": {"w": 256, "h": 222}, "rotated": false, "offset": {"x": 0, "y": 0}}, "a1358036": {"frame": {"x": 361, "y": 3614, "w": 214, "h": 256}, "spriteSourceSize": {"x": 0, "y": 0, "w": 256, "h": 214}, "sourceSize": {"w": 256, "h": 214}, "rotated": true, "offset": {"x": 0, "y": 0}}, "a1358040": {"frame": {"x": 1573, "y": 2582, "w": 211, "h": 256}, "spriteSourceSize": {"x": 0, "y": 0, "w": 256, "h": 211}, "sourceSize": {"w": 256, "h": 211}, "rotated": true, "offset": {"x": 0, "y": 0}}, "a1358041": {"frame": {"x": 3356, "y": 3872, "w": 256, "h": 213}, "spriteSourceSize": {"x": 0, "y": 0, "w": 256, "h": 213}, "sourceSize": {"w": 256, "h": 213}, "rotated": false, "offset": {"x": 0, "y": 0}}, "a1358043": {"frame": {"x": 2033, "y": 518, "w": 209, "h": 256}, "spriteSourceSize": {"x": 0, "y": 0, "w": 256, "h": 209}, "sourceSize": {"w": 256, "h": 209}, "rotated": true, "offset": {"x": 0, "y": 0}}, "a1358048": {"frame": {"x": 184, "y": 1550, "w": 217, "h": 256}, "spriteSourceSize": {"x": 0, "y": 0, "w": 256, "h": 217}, "sourceSize": {"w": 256, "h": 217}, "rotated": true, "offset": {"x": 0, "y": 0}}, "a1358051": {"frame": {"x": 3107, "y": 2, "w": 201, "h": 256}, "spriteSourceSize": {"x": 0, "y": 0, "w": 256, "h": 201}, "sourceSize": {"w": 256, "h": 201}, "rotated": true, "offset": {"x": 0, "y": 0}}, "a1358053": {"frame": {"x": 1034, "y": 3872, "w": 256, "h": 222}, "spriteSourceSize": {"x": 0, "y": 0, "w": 256, "h": 222}, "sourceSize": {"w": 256, "h": 222}, "rotated": false, "offset": {"x": 0, "y": 0}}, "a1358062": {"frame": {"x": 739, "y": 3098, "w": 214, "h": 256}, "spriteSourceSize": {"x": 0, "y": 0, "w": 256, "h": 214}, "sourceSize": {"w": 256, "h": 214}, "rotated": true, "offset": {"x": 0, "y": 0}}, "a1358065": {"frame": {"x": 344, "y": 2066, "w": 216, "h": 256}, "spriteSourceSize": {"x": 0, "y": 0, "w": 256, "h": 216}, "sourceSize": {"w": 256, "h": 216}, "rotated": true, "offset": {"x": 0, "y": 0}}, "a1358068": {"frame": {"x": 2840, "y": 3872, "w": 256, "h": 221}, "spriteSourceSize": {"x": 0, "y": 0, "w": 256, "h": 221}, "sourceSize": {"w": 256, "h": 221}, "rotated": false, "offset": {"x": 0, "y": 0}}, "a1358085": {"frame": {"x": 700, "y": 518, "w": 215, "h": 256}, "spriteSourceSize": {"x": 0, "y": 0, "w": 256, "h": 215}, "sourceSize": {"w": 256, "h": 215}, "rotated": true, "offset": {"x": 0, "y": 0}}, "a1358090": {"frame": {"x": 1918, "y": 2066, "w": 214, "h": 256}, "spriteSourceSize": {"x": 0, "y": 0, "w": 256, "h": 214}, "sourceSize": {"w": 256, "h": 214}, "rotated": true, "offset": {"x": 0, "y": 0}}, "a1358091": {"frame": {"x": 3098, "y": 3872, "w": 256, "h": 219}, "spriteSourceSize": {"x": 0, "y": 0, "w": 256, "h": 219}, "sourceSize": {"w": 256, "h": 219}, "rotated": false, "offset": {"x": 0, "y": 0}}, "a1358095": {"frame": {"x": 3349, "y": 3098, "w": 203, "h": 256}, "spriteSourceSize": {"x": 0, "y": 0, "w": 256, "h": 203}, "sourceSize": {"w": 256, "h": 203}, "rotated": true, "offset": {"x": 0, "y": 0}}, "a1358106": {"frame": {"x": 3364, "y": 2840, "w": 191, "h": 256}, "spriteSourceSize": {"x": 0, "y": 0, "w": 256, "h": 191}, "sourceSize": {"w": 256, "h": 191}, "rotated": true, "offset": {"x": 0, "y": 0}}, "a1358112": {"frame": {"x": 3535, "y": 1292, "w": 210, "h": 256}, "spriteSourceSize": {"x": 0, "y": 0, "w": 256, "h": 210}, "sourceSize": {"w": 256, "h": 210}, "rotated": true, "offset": {"x": 0, "y": 0}}, "a1358120": {"frame": {"x": 168, "y": 2582, "w": 192, "h": 256}, "spriteSourceSize": {"x": 0, "y": 0, "w": 256, "h": 192}, "sourceSize": {"w": 256, "h": 192}, "rotated": true, "offset": {"x": 0, "y": 0}}, "a1358124": {"frame": {"x": 1375, "y": 2582, "w": 196, "h": 256}, "spriteSourceSize": {"x": 0, "y": 0, "w": 256, "h": 196}, "sourceSize": {"w": 256, "h": 196}, "rotated": true, "offset": {"x": 0, "y": 0}}, "a1358125": {"frame": {"x": 1456, "y": 260, "w": 196, "h": 256}, "spriteSourceSize": {"x": 0, "y": 0, "w": 256, "h": 196}, "sourceSize": {"w": 256, "h": 196}, "rotated": true, "offset": {"x": 0, "y": 0}}, "a1358126": {"frame": {"x": 2216, "y": 776, "w": 208, "h": 256}, "spriteSourceSize": {"x": 0, "y": 0, "w": 256, "h": 208}, "sourceSize": {"w": 256, "h": 208}, "rotated": true, "offset": {"x": 0, "y": 0}}, "a1358128": {"frame": {"x": 3666, "y": 1034, "w": 194, "h": 256}, "spriteSourceSize": {"x": 0, "y": 0, "w": 256, "h": 194}, "sourceSize": {"w": 256, "h": 194}, "rotated": true, "offset": {"x": 0, "y": 0}}, "a1358133": {"frame": {"x": 2857, "y": 2066, "w": 190, "h": 256}, "spriteSourceSize": {"x": 0, "y": 0, "w": 256, "h": 190}, "sourceSize": {"w": 256, "h": 190}, "rotated": true, "offset": {"x": 0, "y": 0}}, "a1363004": {"frame": {"x": 2656, "y": 2066, "w": 199, "h": 256}, "spriteSourceSize": {"x": 0, "y": 0, "w": 256, "h": 199}, "sourceSize": {"w": 256, "h": 199}, "rotated": true, "offset": {"x": 0, "y": 0}}, "a1363007": {"frame": {"x": 1102, "y": 260, "w": 176, "h": 256}, "spriteSourceSize": {"x": 0, "y": 0, "w": 176, "h": 256}, "sourceSize": {"w": 176, "h": 256}, "rotated": false, "offset": {"x": 0, "y": 0}}, "a1363008": {"frame": {"x": 1347, "y": 1808, "w": 176, "h": 256}, "spriteSourceSize": {"x": 0, "y": 0, "w": 176, "h": 256}, "sourceSize": {"w": 176, "h": 256}, "rotated": false, "offset": {"x": 0, "y": 0}}, "a1363009": {"frame": {"x": 2540, "y": 2582, "w": 193, "h": 256}, "spriteSourceSize": {"x": 0, "y": 0, "w": 256, "h": 193}, "sourceSize": {"w": 256, "h": 193}, "rotated": true, "offset": {"x": 0, "y": 0}}, "a1363010": {"frame": {"x": 3122, "y": 1550, "w": 192, "h": 256}, "spriteSourceSize": {"x": 0, "y": 0, "w": 256, "h": 192}, "sourceSize": {"w": 256, "h": 192}, "rotated": true, "offset": {"x": 0, "y": 0}}, "a1363021": {"frame": {"x": 1783, "y": 2324, "w": 218, "h": 256}, "spriteSourceSize": {"x": 0, "y": 0, "w": 218, "h": 256}, "sourceSize": {"w": 218, "h": 256}, "rotated": false, "offset": {"x": 0, "y": 0}}, "a1363036": {"frame": {"x": 2086, "y": 1292, "w": 151, "h": 256}, "spriteSourceSize": {"x": 0, "y": 0, "w": 151, "h": 256}, "sourceSize": {"w": 151, "h": 256}, "rotated": false, "offset": {"x": 0, "y": 0}}, "a1363052": {"frame": {"x": 562, "y": 2066, "w": 197, "h": 256}, "spriteSourceSize": {"x": 0, "y": 0, "w": 256, "h": 197}, "sourceSize": {"w": 256, "h": 197}, "rotated": true, "offset": {"x": 0, "y": 0}}, "a1363057": {"frame": {"x": 936, "y": 1292, "w": 192, "h": 256}, "spriteSourceSize": {"x": 0, "y": 0, "w": 256, "h": 192}, "sourceSize": {"w": 256, "h": 192}, "rotated": true, "offset": {"x": 0, "y": 0}}, "a1363060": {"frame": {"x": 1404, "y": 2324, "w": 186, "h": 256}, "spriteSourceSize": {"x": 0, "y": 0, "w": 256, "h": 186}, "sourceSize": {"w": 256, "h": 186}, "rotated": true, "offset": {"x": 0, "y": 0}}, "a1367004": {"frame": {"x": 761, "y": 2066, "w": 174, "h": 256}, "spriteSourceSize": {"x": 0, "y": 0, "w": 174, "h": 256}, "sourceSize": {"w": 174, "h": 256}, "rotated": false, "offset": {"x": 0, "y": 0}}, "a1367005": {"frame": {"x": 3872, "y": 3356, "w": 187, "h": 256}, "spriteSourceSize": {"x": 0, "y": 0, "w": 187, "h": 256}, "sourceSize": {"w": 187, "h": 256}, "rotated": false, "offset": {"x": 0, "y": 0}}, "a1367011": {"frame": {"x": 1672, "y": 776, "w": 184, "h": 256}, "spriteSourceSize": {"x": 0, "y": 0, "w": 256, "h": 184}, "sourceSize": {"w": 256, "h": 184}, "rotated": true, "offset": {"x": 0, "y": 0}}, "a1367012": {"frame": {"x": 1472, "y": 3356, "w": 209, "h": 256}, "spriteSourceSize": {"x": 0, "y": 0, "w": 256, "h": 209}, "sourceSize": {"w": 256, "h": 209}, "rotated": true, "offset": {"x": 0, "y": 0}}, "a1367013": {"frame": {"x": 2, "y": 1034, "w": 183, "h": 256}, "spriteSourceSize": {"x": 0, "y": 0, "w": 256, "h": 183}, "sourceSize": {"w": 256, "h": 183}, "rotated": true, "offset": {"x": 0, "y": 0}}, "a1367014": {"frame": {"x": 1280, "y": 260, "w": 174, "h": 256}, "spriteSourceSize": {"x": 0, "y": 0, "w": 256, "h": 174}, "sourceSize": {"w": 256, "h": 174}, "rotated": true, "offset": {"x": 0, "y": 0}}, "a1367016": {"frame": {"x": 2430, "y": 3098, "w": 153, "h": 256}, "spriteSourceSize": {"x": 0, "y": 0, "w": 256, "h": 153}, "sourceSize": {"w": 256, "h": 153}, "rotated": true, "offset": {"x": 0, "y": 0}}, "a1367020": {"frame": {"x": 3297, "y": 3356, "w": 178, "h": 256}, "spriteSourceSize": {"x": 0, "y": 0, "w": 256, "h": 178}, "sourceSize": {"w": 256, "h": 178}, "rotated": true, "offset": {"x": 0, "y": 0}}, "a1367021": {"frame": {"x": 3251, "y": 2324, "w": 167, "h": 256}, "spriteSourceSize": {"x": 0, "y": 0, "w": 256, "h": 167}, "sourceSize": {"w": 256, "h": 167}, "rotated": true, "offset": {"x": 0, "y": 0}}, "a1367025": {"frame": {"x": 2754, "y": 1808, "w": 172, "h": 256}, "spriteSourceSize": {"x": 0, "y": 0, "w": 256, "h": 172}, "sourceSize": {"w": 256, "h": 172}, "rotated": true, "offset": {"x": 0, "y": 0}}, "a1367030": {"frame": {"x": 2, "y": 3356, "w": 144, "h": 256}, "spriteSourceSize": {"x": 0, "y": 0, "w": 256, "h": 144}, "sourceSize": {"w": 256, "h": 144}, "rotated": true, "offset": {"x": 0, "y": 0}}, "a1367044": {"frame": {"x": 2, "y": 3098, "w": 210, "h": 256}, "spriteSourceSize": {"x": 0, "y": 0, "w": 256, "h": 210}, "sourceSize": {"w": 256, "h": 210}, "rotated": true, "offset": {"x": 0, "y": 0}}, "a1367046": {"frame": {"x": 2937, "y": 1034, "w": 186, "h": 256}, "spriteSourceSize": {"x": 0, "y": 0, "w": 256, "h": 186}, "sourceSize": {"w": 256, "h": 186}, "rotated": true, "offset": {"x": 0, "y": 0}}, "a1367050": {"frame": {"x": 3178, "y": 260, "w": 209, "h": 256}, "spriteSourceSize": {"x": 0, "y": 0, "w": 256, "h": 209}, "sourceSize": {"w": 256, "h": 209}, "rotated": true, "offset": {"x": 0, "y": 0}}, "a1367054": {"frame": {"x": 2367, "y": 2, "w": 230, "h": 256}, "spriteSourceSize": {"x": 0, "y": 0, "w": 230, "h": 256}, "sourceSize": {"w": 230, "h": 256}, "rotated": false, "offset": {"x": 0, "y": 0}}, "a1367062": {"frame": {"x": 2223, "y": 260, "w": 205, "h": 256}, "spriteSourceSize": {"x": 0, "y": 0, "w": 256, "h": 205}, "sourceSize": {"w": 256, "h": 205}, "rotated": true, "offset": {"x": 0, "y": 0}}, "a1367067": {"frame": {"x": 722, "y": 260, "w": 172, "h": 256}, "spriteSourceSize": {"x": 0, "y": 0, "w": 172, "h": 256}, "sourceSize": {"w": 172, "h": 256}, "rotated": false, "offset": {"x": 0, "y": 0}}, "a1367075": {"frame": {"x": 2628, "y": 1808, "w": 124, "h": 256}, "spriteSourceSize": {"x": 0, "y": 0, "w": 256, "h": 124}, "sourceSize": {"w": 256, "h": 124}, "rotated": true, "offset": {"x": 0, "y": 0}}, "a1367081": {"frame": {"x": 2546, "y": 2324, "w": 183, "h": 256}, "spriteSourceSize": {"x": 0, "y": 0, "w": 256, "h": 183}, "sourceSize": {"w": 256, "h": 183}, "rotated": true, "offset": {"x": 0, "y": 0}}, "a1367082": {"frame": {"x": 360, "y": 260, "w": 172, "h": 256}, "spriteSourceSize": {"x": 0, "y": 0, "w": 256, "h": 172}, "sourceSize": {"w": 256, "h": 172}, "rotated": true, "offset": {"x": 0, "y": 0}}, "a1367083": {"frame": {"x": 1866, "y": 2840, "w": 181, "h": 256}, "spriteSourceSize": {"x": 0, "y": 0, "w": 256, "h": 181}, "sourceSize": {"w": 256, "h": 181}, "rotated": true, "offset": {"x": 0, "y": 0}}, "a1367084": {"frame": {"x": 2445, "y": 1292, "w": 190, "h": 256}, "spriteSourceSize": {"x": 0, "y": 0, "w": 256, "h": 190}, "sourceSize": {"w": 256, "h": 190}, "rotated": true, "offset": {"x": 0, "y": 0}}, "a1367085": {"frame": {"x": 3492, "y": 2066, "w": 188, "h": 256}, "spriteSourceSize": {"x": 0, "y": 0, "w": 256, "h": 188}, "sourceSize": {"w": 256, "h": 188}, "rotated": true, "offset": {"x": 0, "y": 0}}, "a1367088": {"frame": {"x": 2430, "y": 260, "w": 198, "h": 256}, "spriteSourceSize": {"x": 0, "y": 0, "w": 256, "h": 198}, "sourceSize": {"w": 256, "h": 198}, "rotated": true, "offset": {"x": 0, "y": 0}}, "a1367091": {"frame": {"x": 1091, "y": 1034, "w": 171, "h": 256}, "spriteSourceSize": {"x": 0, "y": 0, "w": 256, "h": 171}, "sourceSize": {"w": 256, "h": 171}, "rotated": true, "offset": {"x": 0, "y": 0}}, "a1367108": {"frame": {"x": 387, "y": 3098, "w": 178, "h": 256}, "spriteSourceSize": {"x": 0, "y": 0, "w": 256, "h": 178}, "sourceSize": {"w": 256, "h": 178}, "rotated": true, "offset": {"x": 0, "y": 0}}, "a1367110": {"frame": {"x": 706, "y": 1034, "w": 217, "h": 256}, "spriteSourceSize": {"x": 0, "y": 0, "w": 217, "h": 256}, "sourceSize": {"w": 217, "h": 256}, "rotated": false, "offset": {"x": 0, "y": 0}}, "a1367111": {"frame": {"x": 722, "y": 776, "w": 214, "h": 256}, "spriteSourceSize": {"x": 0, "y": 0, "w": 214, "h": 256}, "sourceSize": {"w": 214, "h": 256}, "rotated": false, "offset": {"x": 0, "y": 0}}, "a1367138": {"frame": {"x": 2532, "y": 1034, "w": 203, "h": 256}, "spriteSourceSize": {"x": 0, "y": 0, "w": 256, "h": 203}, "sourceSize": {"w": 256, "h": 203}, "rotated": true, "offset": {"x": 0, "y": 0}}, "a1367150": {"frame": {"x": 3966, "y": 647, "w": 123, "h": 256}, "spriteSourceSize": {"x": 0, "y": 0, "w": 256, "h": 123}, "sourceSize": {"w": 256, "h": 123}, "rotated": true, "offset": {"x": 0, "y": 0}}, "a1367166": {"frame": {"x": 2908, "y": 2582, "w": 181, "h": 256}, "spriteSourceSize": {"x": 0, "y": 0, "w": 256, "h": 181}, "sourceSize": {"w": 256, "h": 181}, "rotated": true, "offset": {"x": 0, "y": 0}}, "a1367175": {"frame": {"x": 2647, "y": 776, "w": 159, "h": 256}, "spriteSourceSize": {"x": 0, "y": 0, "w": 256, "h": 159}, "sourceSize": {"w": 256, "h": 159}, "rotated": true, "offset": {"x": 0, "y": 0}}, "a1367185": {"frame": {"x": 2410, "y": 3356, "w": 176, "h": 256}, "spriteSourceSize": {"x": 0, "y": 0, "w": 256, "h": 176}, "sourceSize": {"w": 256, "h": 176}, "rotated": true, "offset": {"x": 0, "y": 0}}, "a1367195": {"frame": {"x": 1264, "y": 1034, "w": 171, "h": 256}, "spriteSourceSize": {"x": 0, "y": 0, "w": 171, "h": 256}, "sourceSize": {"w": 171, "h": 256}, "rotated": false, "offset": {"x": 0, "y": 0}}, "a1367197": {"frame": {"x": 1112, "y": 3614, "w": 144, "h": 256}, "spriteSourceSize": {"x": 0, "y": 0, "w": 256, "h": 144}, "sourceSize": {"w": 256, "h": 144}, "rotated": true, "offset": {"x": 0, "y": 0}}, "a1367201": {"frame": {"x": 2003, "y": 2324, "w": 172, "h": 256}, "spriteSourceSize": {"x": 0, "y": 0, "w": 256, "h": 172}, "sourceSize": {"w": 256, "h": 172}, "rotated": true, "offset": {"x": 0, "y": 0}}, "a1367203": {"frame": {"x": 553, "y": 2840, "w": 170, "h": 256}, "spriteSourceSize": {"x": 0, "y": 0, "w": 256, "h": 170}, "sourceSize": {"w": 256, "h": 170}, "rotated": true, "offset": {"x": 0, "y": 0}}, "a1367205": {"frame": {"x": 1698, "y": 3098, "w": 189, "h": 256}, "spriteSourceSize": {"x": 0, "y": 0, "w": 256, "h": 189}, "sourceSize": {"w": 256, "h": 189}, "rotated": true, "offset": {"x": 0, "y": 0}}, "a1367206": {"frame": {"x": 2, "y": 2840, "w": 172, "h": 256}, "spriteSourceSize": {"x": 0, "y": 0, "w": 256, "h": 172}, "sourceSize": {"w": 256, "h": 172}, "rotated": true, "offset": {"x": 0, "y": 0}}, "a1367209": {"frame": {"x": 943, "y": 1808, "w": 207, "h": 256}, "spriteSourceSize": {"x": 0, "y": 0, "w": 256, "h": 207}, "sourceSize": {"w": 256, "h": 207}, "rotated": true, "offset": {"x": 0, "y": 0}}, "a1367214": {"frame": {"x": 152, "y": 518, "w": 180, "h": 256}, "spriteSourceSize": {"x": 0, "y": 0, "w": 256, "h": 180}, "sourceSize": {"w": 256, "h": 180}, "rotated": true, "offset": {"x": 0, "y": 0}}, "a1367216": {"frame": {"x": 1858, "y": 776, "w": 182, "h": 256}, "spriteSourceSize": {"x": 0, "y": 0, "w": 256, "h": 182}, "sourceSize": {"w": 256, "h": 182}, "rotated": true, "offset": {"x": 0, "y": 0}}, "a1367221": {"frame": {"x": 1626, "y": 2, "w": 187, "h": 256}, "spriteSourceSize": {"x": 0, "y": 0, "w": 256, "h": 187}, "sourceSize": {"w": 256, "h": 187}, "rotated": true, "offset": {"x": 0, "y": 0}}, "a1367222": {"frame": {"x": 2795, "y": 260, "w": 190, "h": 256}, "spriteSourceSize": {"x": 0, "y": 0, "w": 256, "h": 190}, "sourceSize": {"w": 256, "h": 190}, "rotated": true, "offset": {"x": 0, "y": 0}}, "a1367224": {"frame": {"x": 2487, "y": 2066, "w": 167, "h": 256}, "spriteSourceSize": {"x": 0, "y": 0, "w": 256, "h": 167}, "sourceSize": {"w": 256, "h": 167}, "rotated": true, "offset": {"x": 0, "y": 0}}, "a1367228": {"frame": {"x": 2835, "y": 2840, "w": 189, "h": 256}, "spriteSourceSize": {"x": 0, "y": 0, "w": 189, "h": 256}, "sourceSize": {"w": 189, "h": 256}, "rotated": false, "offset": {"x": 0, "y": 0}}, "a1367229": {"frame": {"x": 3342, "y": 1292, "w": 191, "h": 256}, "spriteSourceSize": {"x": 0, "y": 0, "w": 256, "h": 191}, "sourceSize": {"w": 256, "h": 191}, "rotated": true, "offset": {"x": 0, "y": 0}}, "a1367236": {"frame": {"x": 744, "y": 3356, "w": 195, "h": 256}, "spriteSourceSize": {"x": 0, "y": 0, "w": 256, "h": 195}, "sourceSize": {"w": 256, "h": 195}, "rotated": true, "offset": {"x": 0, "y": 0}}, "a1367237": {"frame": {"x": 2134, "y": 2066, "w": 169, "h": 256}, "spriteSourceSize": {"x": 0, "y": 0, "w": 256, "h": 169}, "sourceSize": {"w": 256, "h": 169}, "rotated": true, "offset": {"x": 0, "y": 0}}, "a1367253": {"frame": {"x": 1490, "y": 518, "w": 173, "h": 256}, "spriteSourceSize": {"x": 0, "y": 0, "w": 256, "h": 173}, "sourceSize": {"w": 256, "h": 173}, "rotated": true, "offset": {"x": 0, "y": 0}}, "a1367256": {"frame": {"x": 2075, "y": 1808, "w": 175, "h": 256}, "spriteSourceSize": {"x": 0, "y": 0, "w": 256, "h": 175}, "sourceSize": {"w": 256, "h": 175}, "rotated": true, "offset": {"x": 0, "y": 0}}, "a1367278": {"frame": {"x": 1200, "y": 2582, "w": 173, "h": 256}, "spriteSourceSize": {"x": 0, "y": 0, "w": 256, "h": 173}, "sourceSize": {"w": 256, "h": 173}, "rotated": true, "offset": {"x": 0, "y": 0}}, "a1367279": {"frame": {"x": 3026, "y": 2840, "w": 172, "h": 256}, "spriteSourceSize": {"x": 0, "y": 0, "w": 256, "h": 172}, "sourceSize": {"w": 256, "h": 172}, "rotated": true, "offset": {"x": 0, "y": 0}}, "a1367280": {"frame": {"x": 771, "y": 2582, "w": 231, "h": 256}, "spriteSourceSize": {"x": 0, "y": 0, "w": 256, "h": 231}, "sourceSize": {"w": 256, "h": 231}, "rotated": true, "offset": {"x": 0, "y": 0}}, "a1367295": {"frame": {"x": 2049, "y": 2840, "w": 193, "h": 256}, "spriteSourceSize": {"x": 0, "y": 0, "w": 256, "h": 193}, "sourceSize": {"w": 256, "h": 193}, "rotated": true, "offset": {"x": 0, "y": 0}}, "a1367304": {"frame": {"x": 868, "y": 2324, "w": 148, "h": 256}, "spriteSourceSize": {"x": 0, "y": 0, "w": 256, "h": 148}, "sourceSize": {"w": 256, "h": 148}, "rotated": true, "offset": {"x": 0, "y": 0}}, "a1367307": {"frame": {"x": 1861, "y": 1550, "w": 173, "h": 256}, "spriteSourceSize": {"x": 0, "y": 0, "w": 256, "h": 173}, "sourceSize": {"w": 256, "h": 173}, "rotated": true, "offset": {"x": 0, "y": 0}}, "a1367312": {"frame": {"x": 881, "y": 2840, "w": 178, "h": 256}, "spriteSourceSize": {"x": 0, "y": 0, "w": 256, "h": 178}, "sourceSize": {"w": 256, "h": 178}, "rotated": true, "offset": {"x": 0, "y": 0}}, "a1367314": {"frame": {"x": 2928, "y": 1808, "w": 177, "h": 256}, "spriteSourceSize": {"x": 0, "y": 0, "w": 256, "h": 177}, "sourceSize": {"w": 256, "h": 177}, "rotated": true, "offset": {"x": 0, "y": 0}}, "a1367322": {"frame": {"x": 3661, "y": 1808, "w": 167, "h": 256}, "spriteSourceSize": {"x": 0, "y": 0, "w": 256, "h": 167}, "sourceSize": {"w": 256, "h": 167}, "rotated": true, "offset": {"x": 0, "y": 0}}, "a1367323": {"frame": {"x": 344, "y": 776, "w": 181, "h": 256}, "spriteSourceSize": {"x": 0, "y": 0, "w": 256, "h": 181}, "sourceSize": {"w": 256, "h": 181}, "rotated": true, "offset": {"x": 0, "y": 0}}, "a1367330": {"frame": {"x": 3182, "y": 1292, "w": 158, "h": 256}, "spriteSourceSize": {"x": 0, "y": 0, "w": 256, "h": 158}, "sourceSize": {"w": 256, "h": 158}, "rotated": true, "offset": {"x": 0, "y": 0}}, "a1367332": {"frame": {"x": 3086, "y": 3614, "w": 192, "h": 256}, "spriteSourceSize": {"x": 0, "y": 0, "w": 192, "h": 256}, "sourceSize": {"w": 192, "h": 256}, "rotated": false, "offset": {"x": 0, "y": 0}}, "a1367340": {"frame": {"x": 2, "y": 518, "w": 148, "h": 256}, "spriteSourceSize": {"x": 0, "y": 0, "w": 256, "h": 148}, "sourceSize": {"w": 256, "h": 148}, "rotated": true, "offset": {"x": 0, "y": 0}}, "a1367341": {"frame": {"x": 3493, "y": 1034, "w": 171, "h": 256}, "spriteSourceSize": {"x": 0, "y": 0, "w": 256, "h": 171}, "sourceSize": {"w": 256, "h": 171}, "rotated": true, "offset": {"x": 0, "y": 0}}, "a1367347": {"frame": {"x": 1550, "y": 3872, "w": 256, "h": 222}, "spriteSourceSize": {"x": 0, "y": 0, "w": 256, "h": 222}, "sourceSize": {"w": 256, "h": 222}, "rotated": false, "offset": {"x": 0, "y": 0}}, "a1367351": {"frame": {"x": 570, "y": 2, "w": 177, "h": 256}, "spriteSourceSize": {"x": 0, "y": 0, "w": 256, "h": 177}, "sourceSize": {"w": 256, "h": 177}, "rotated": true, "offset": {"x": 0, "y": 0}}, "a1367357": {"frame": {"x": 3663, "y": 1550, "w": 180, "h": 256}, "spriteSourceSize": {"x": 0, "y": 0, "w": 256, "h": 180}, "sourceSize": {"w": 256, "h": 180}, "rotated": true, "offset": {"x": 0, "y": 0}}, "a1367359": {"frame": {"x": 3280, "y": 3614, "w": 177, "h": 256}, "spriteSourceSize": {"x": 0, "y": 0, "w": 256, "h": 177}, "sourceSize": {"w": 256, "h": 177}, "rotated": true, "offset": {"x": 0, "y": 0}}, "a1367361": {"frame": {"x": 2369, "y": 1034, "w": 161, "h": 256}, "spriteSourceSize": {"x": 0, "y": 0, "w": 256, "h": 161}, "sourceSize": {"w": 256, "h": 161}, "rotated": true, "offset": {"x": 0, "y": 0}}, "a1367365": {"frame": {"x": 2, "y": 260, "w": 182, "h": 256}, "spriteSourceSize": {"x": 0, "y": 0, "w": 256, "h": 182}, "sourceSize": {"w": 256, "h": 182}, "rotated": true, "offset": {"x": 0, "y": 0}}, "a1367368": {"frame": {"x": 534, "y": 260, "w": 186, "h": 256}, "spriteSourceSize": {"x": 0, "y": 0, "w": 256, "h": 186}, "sourceSize": {"w": 256, "h": 186}, "rotated": true, "offset": {"x": 0, "y": 0}}, "a1367369": {"frame": {"x": 1152, "y": 1808, "w": 193, "h": 256}, "spriteSourceSize": {"x": 0, "y": 0, "w": 256, "h": 193}, "sourceSize": {"w": 256, "h": 193}, "rotated": true, "offset": {"x": 0, "y": 0}}, "a1367371": {"frame": {"x": 3250, "y": 2066, "w": 240, "h": 256}, "spriteSourceSize": {"x": 0, "y": 0, "w": 240, "h": 256}, "sourceSize": {"w": 240, "h": 256}, "rotated": false, "offset": {"x": 0, "y": 0}}, "a1367372": {"frame": {"x": 1706, "y": 1292, "w": 210, "h": 256}, "spriteSourceSize": {"x": 0, "y": 0, "w": 256, "h": 210}, "sourceSize": {"w": 256, "h": 210}, "rotated": true, "offset": {"x": 0, "y": 0}}, "a1367375": {"frame": {"x": 3680, "y": 3356, "w": 177, "h": 256}, "spriteSourceSize": {"x": 0, "y": 0, "w": 256, "h": 177}, "sourceSize": {"w": 256, "h": 177}, "rotated": true, "offset": {"x": 0, "y": 0}}, "a1367377": {"frame": {"x": 2214, "y": 1550, "w": 182, "h": 256}, "spriteSourceSize": {"x": 0, "y": 0, "w": 256, "h": 182}, "sourceSize": {"w": 256, "h": 182}, "rotated": true, "offset": {"x": 0, "y": 0}}, "a1367382": {"frame": {"x": 1292, "y": 3872, "w": 256, "h": 186}, "spriteSourceSize": {"x": 0, "y": 0, "w": 256, "h": 186}, "sourceSize": {"w": 256, "h": 186}, "rotated": false, "offset": {"x": 0, "y": 0}}, "a1367383": {"frame": {"x": 1525, "y": 1808, "w": 175, "h": 256}, "spriteSourceSize": {"x": 0, "y": 0, "w": 256, "h": 175}, "sourceSize": {"w": 256, "h": 175}, "rotated": true, "offset": {"x": 0, "y": 0}}, "a1367386": {"frame": {"x": 749, "y": 2, "w": 181, "h": 256}, "spriteSourceSize": {"x": 0, "y": 0, "w": 256, "h": 181}, "sourceSize": {"w": 256, "h": 181}, "rotated": true, "offset": {"x": 0, "y": 0}}, "a1367389": {"frame": {"x": 2582, "y": 3872, "w": 256, "h": 179}, "spriteSourceSize": {"x": 0, "y": 0, "w": 256, "h": 179}, "sourceSize": {"w": 256, "h": 179}, "rotated": false, "offset": {"x": 0, "y": 0}}, "a1367390": {"frame": {"x": 2, "y": 1292, "w": 171, "h": 256}, "spriteSourceSize": {"x": 0, "y": 0, "w": 256, "h": 171}, "sourceSize": {"w": 256, "h": 171}, "rotated": true, "offset": {"x": 0, "y": 0}}, "a1367391": {"frame": {"x": 3160, "y": 3098, "w": 187, "h": 256}, "spriteSourceSize": {"x": 0, "y": 0, "w": 256, "h": 187}, "sourceSize": {"w": 256, "h": 187}, "rotated": true, "offset": {"x": 0, "y": 0}}, "a1367392": {"frame": {"x": 1108, "y": 3356, "w": 175, "h": 256}, "spriteSourceSize": {"x": 0, "y": 0, "w": 256, "h": 175}, "sourceSize": {"w": 256, "h": 175}, "rotated": true, "offset": {"x": 0, "y": 0}}, "a1367403": {"frame": {"x": 2354, "y": 2582, "w": 184, "h": 256}, "spriteSourceSize": {"x": 0, "y": 0, "w": 256, "h": 184}, "sourceSize": {"w": 256, "h": 184}, "rotated": true, "offset": {"x": 0, "y": 0}}, "a1367415": {"frame": {"x": 2637, "y": 1292, "w": 183, "h": 256}, "spriteSourceSize": {"x": 0, "y": 0, "w": 256, "h": 183}, "sourceSize": {"w": 256, "h": 183}, "rotated": true, "offset": {"x": 0, "y": 0}}, "a1367420": {"frame": {"x": 2066, "y": 3872, "w": 256, "h": 171}, "spriteSourceSize": {"x": 0, "y": 0, "w": 256, "h": 171}, "sourceSize": {"w": 256, "h": 171}, "rotated": false, "offset": {"x": 0, "y": 0}}, "a1367425": {"frame": {"x": 2200, "y": 2, "w": 165, "h": 256}, "spriteSourceSize": {"x": 0, "y": 0, "w": 256, "h": 165}, "sourceSize": {"w": 256, "h": 165}, "rotated": true, "offset": {"x": 0, "y": 0}}, "a1367429": {"frame": {"x": 552, "y": 1034, "w": 152, "h": 256}, "spriteSourceSize": {"x": 0, "y": 0, "w": 256, "h": 152}, "sourceSize": {"w": 256, "h": 152}, "rotated": true, "offset": {"x": 0, "y": 0}}, "a1367431": {"frame": {"x": 378, "y": 2324, "w": 146, "h": 256}, "spriteSourceSize": {"x": 0, "y": 0, "w": 146, "h": 256}, "sourceSize": {"w": 146, "h": 256}, "rotated": false, "offset": {"x": 0, "y": 0}}, "a1367433": {"frame": {"x": 2052, "y": 3356, "w": 147, "h": 256}, "spriteSourceSize": {"x": 0, "y": 0, "w": 256, "h": 147}, "sourceSize": {"w": 256, "h": 147}, "rotated": true, "offset": {"x": 0, "y": 0}}, "a1367435": {"frame": {"x": 1897, "y": 3356, "w": 153, "h": 256}, "spriteSourceSize": {"x": 0, "y": 0, "w": 256, "h": 153}, "sourceSize": {"w": 256, "h": 153}, "rotated": true, "offset": {"x": 0, "y": 0}}, "a1367443": {"frame": {"x": 3872, "y": 3614, "w": 197, "h": 256}, "spriteSourceSize": {"x": 0, "y": 0, "w": 197, "h": 256}, "sourceSize": {"w": 197, "h": 256}, "rotated": false, "offset": {"x": 0, "y": 0}}, "a1367452": {"frame": {"x": 2344, "y": 2324, "w": 200, "h": 256}, "spriteSourceSize": {"x": 0, "y": 0, "w": 256, "h": 200}, "sourceSize": {"w": 256, "h": 200}, "rotated": true, "offset": {"x": 0, "y": 0}}, "a1367456": {"frame": {"x": 2, "y": 2324, "w": 179, "h": 256}, "spriteSourceSize": {"x": 0, "y": 0, "w": 256, "h": 179}, "sourceSize": {"w": 256, "h": 179}, "rotated": true, "offset": {"x": 0, "y": 0}}, "a1367459": {"frame": {"x": 562, "y": 3356, "w": 180, "h": 256}, "spriteSourceSize": {"x": 0, "y": 0, "w": 180, "h": 256}, "sourceSize": {"w": 180, "h": 256}, "rotated": false, "offset": {"x": 0, "y": 0}}, "a1367461": {"frame": {"x": 3184, "y": 776, "w": 179, "h": 256}, "spriteSourceSize": {"x": 0, "y": 0, "w": 256, "h": 179}, "sourceSize": {"w": 256, "h": 179}, "rotated": true, "offset": {"x": 0, "y": 0}}, "a1367477": {"frame": {"x": 3064, "y": 2324, "w": 185, "h": 256}, "spriteSourceSize": {"x": 0, "y": 0, "w": 256, "h": 185}, "sourceSize": {"w": 256, "h": 185}, "rotated": true, "offset": {"x": 0, "y": 0}}, "a1367481": {"frame": {"x": 404, "y": 2, "w": 164, "h": 256}, "spriteSourceSize": {"x": 0, "y": 0, "w": 256, "h": 164}, "sourceSize": {"w": 256, "h": 164}, "rotated": true, "offset": {"x": 0, "y": 0}}, "a1367493": {"frame": {"x": 2987, "y": 260, "w": 189, "h": 256}, "spriteSourceSize": {"x": 0, "y": 0, "w": 256, "h": 189}, "sourceSize": {"w": 256, "h": 189}, "rotated": true, "offset": {"x": 0, "y": 0}}, "a1367496": {"frame": {"x": 3747, "y": 1292, "w": 217, "h": 256}, "spriteSourceSize": {"x": 0, "y": 0, "w": 256, "h": 217}, "sourceSize": {"w": 256, "h": 217}, "rotated": true, "offset": {"x": 0, "y": 0}}, "a1367499": {"frame": {"x": 2966, "y": 3098, "w": 192, "h": 256}, "spriteSourceSize": {"x": 0, "y": 0, "w": 256, "h": 192}, "sourceSize": {"w": 256, "h": 192}, "rotated": true, "offset": {"x": 0, "y": 0}}, "a1367527": {"frame": {"x": 3469, "y": 2582, "w": 205, "h": 256}, "spriteSourceSize": {"x": 0, "y": 0, "w": 256, "h": 205}, "sourceSize": {"w": 256, "h": 205}, "rotated": true, "offset": {"x": 0, "y": 0}}, "a1367532": {"frame": {"x": 725, "y": 2840, "w": 154, "h": 256}, "spriteSourceSize": {"x": 0, "y": 0, "w": 256, "h": 154}, "sourceSize": {"w": 256, "h": 154}, "rotated": true, "offset": {"x": 0, "y": 0}}, "a1367553": {"frame": {"x": 1004, "y": 2582, "w": 194, "h": 256}, "spriteSourceSize": {"x": 0, "y": 0, "w": 256, "h": 194}, "sourceSize": {"w": 256, "h": 194}, "rotated": true, "offset": {"x": 0, "y": 0}}, "a1367554": {"frame": {"x": 1786, "y": 2582, "w": 169, "h": 256}, "spriteSourceSize": {"x": 0, "y": 0, "w": 256, "h": 169}, "sourceSize": {"w": 256, "h": 169}, "rotated": true, "offset": {"x": 0, "y": 0}}, "a1367558": {"frame": {"x": 423, "y": 1808, "w": 160, "h": 256}, "spriteSourceSize": {"x": 0, "y": 0, "w": 256, "h": 160}, "sourceSize": {"w": 256, "h": 160}, "rotated": true, "offset": {"x": 0, "y": 0}}, "a1367560": {"frame": {"x": 925, "y": 1034, "w": 164, "h": 256}, "spriteSourceSize": {"x": 0, "y": 0, "w": 256, "h": 164}, "sourceSize": {"w": 256, "h": 164}, "rotated": true, "offset": {"x": 0, "y": 0}}, "a1367561": {"frame": {"x": 1889, "y": 3098, "w": 167, "h": 256}, "spriteSourceSize": {"x": 0, "y": 0, "w": 256, "h": 167}, "sourceSize": {"w": 256, "h": 167}, "rotated": true, "offset": {"x": 0, "y": 0}}, "a1367563": {"frame": {"x": 776, "y": 3872, "w": 256, "h": 154}, "spriteSourceSize": {"x": 0, "y": 0, "w": 256, "h": 154}, "sourceSize": {"w": 256, "h": 154}, "rotated": false, "offset": {"x": 0, "y": 0}}, "a1367568": {"frame": {"x": 1258, "y": 2840, "w": 191, "h": 256}, "spriteSourceSize": {"x": 0, "y": 0, "w": 256, "h": 191}, "sourceSize": {"w": 256, "h": 191}, "rotated": true, "offset": {"x": 0, "y": 0}}, "a1367569": {"frame": {"x": 1957, "y": 2582, "w": 188, "h": 256}, "spriteSourceSize": {"x": 0, "y": 0, "w": 256, "h": 188}, "sourceSize": {"w": 256, "h": 188}, "rotated": true, "offset": {"x": 0, "y": 0}}, "a1367575": {"frame": {"x": 1815, "y": 2, "w": 184, "h": 256}, "spriteSourceSize": {"x": 0, "y": 0, "w": 256, "h": 184}, "sourceSize": {"w": 256, "h": 184}, "rotated": true, "offset": {"x": 0, "y": 0}}, "a1367578": {"frame": {"x": 938, "y": 776, "w": 175, "h": 256}, "spriteSourceSize": {"x": 0, "y": 0, "w": 175, "h": 256}, "sourceSize": {"w": 175, "h": 256}, "rotated": false, "offset": {"x": 0, "y": 0}}, "a1367579": {"frame": {"x": 2169, "y": 3614, "w": 194, "h": 256}, "spriteSourceSize": {"x": 0, "y": 0, "w": 194, "h": 256}, "sourceSize": {"w": 194, "h": 256}, "rotated": false, "offset": {"x": 0, "y": 0}}, "a1367590": {"frame": {"x": 3316, "y": 1550, "w": 192, "h": 256}, "spriteSourceSize": {"x": 0, "y": 0, "w": 256, "h": 192}, "sourceSize": {"w": 256, "h": 192}, "rotated": true, "offset": {"x": 0, "y": 0}}, "a1367591": {"frame": {"x": 2244, "y": 518, "w": 182, "h": 256}, "spriteSourceSize": {"x": 0, "y": 0, "w": 256, "h": 182}, "sourceSize": {"w": 256, "h": 182}, "rotated": true, "offset": {"x": 0, "y": 0}}, "a1367602": {"frame": {"x": 2244, "y": 2840, "w": 187, "h": 256}, "spriteSourceSize": {"x": 0, "y": 0, "w": 256, "h": 187}, "sourceSize": {"w": 256, "h": 187}, "rotated": true, "offset": {"x": 0, "y": 0}}, "a1367615": {"frame": {"x": 1991, "y": 3614, "w": 176, "h": 256}, "spriteSourceSize": {"x": 0, "y": 0, "w": 256, "h": 176}, "sourceSize": {"w": 256, "h": 176}, "rotated": true, "offset": {"x": 0, "y": 0}}, "a1367616": {"frame": {"x": 2762, "y": 2, "w": 178, "h": 256}, "spriteSourceSize": {"x": 0, "y": 0, "w": 256, "h": 178}, "sourceSize": {"w": 256, "h": 178}, "rotated": true, "offset": {"x": 0, "y": 0}}, "a1367626": {"frame": {"x": 3487, "y": 1808, "w": 172, "h": 256}, "spriteSourceSize": {"x": 0, "y": 0, "w": 256, "h": 172}, "sourceSize": {"w": 256, "h": 172}, "rotated": true, "offset": {"x": 0, "y": 0}}, "a1367632": {"frame": {"x": 3708, "y": 776, "w": 145, "h": 256}, "spriteSourceSize": {"x": 0, "y": 0, "w": 145, "h": 256}, "sourceSize": {"w": 145, "h": 256}, "rotated": false, "offset": {"x": 0, "y": 0}}, "a1367634": {"frame": {"x": 2822, "y": 1292, "w": 190, "h": 256}, "spriteSourceSize": {"x": 0, "y": 0, "w": 256, "h": 190}, "sourceSize": {"w": 256, "h": 190}, "rotated": true, "offset": {"x": 0, "y": 0}}, "a1367636": {"frame": {"x": 955, "y": 3098, "w": 178, "h": 256}, "spriteSourceSize": {"x": 0, "y": 0, "w": 256, "h": 178}, "sourceSize": {"w": 256, "h": 178}, "rotated": true, "offset": {"x": 0, "y": 0}}, "a1367639": {"frame": {"x": 3091, "y": 2582, "w": 202, "h": 256}, "spriteSourceSize": {"x": 0, "y": 0, "w": 256, "h": 202}, "sourceSize": {"w": 256, "h": 202}, "rotated": true, "offset": {"x": 0, "y": 0}}, "a1367642": {"frame": {"x": 3726, "y": 3098, "w": 197, "h": 256}, "spriteSourceSize": {"x": 0, "y": 0, "w": 256, "h": 197}, "sourceSize": {"w": 256, "h": 197}, "rotated": true, "offset": {"x": 0, "y": 0}}, "a1367643": {"frame": {"x": 527, "y": 776, "w": 193, "h": 256}, "spriteSourceSize": {"x": 0, "y": 0, "w": 256, "h": 193}, "sourceSize": {"w": 256, "h": 193}, "rotated": true, "offset": {"x": 0, "y": 0}}, "a1367644": {"frame": {"x": 540, "y": 1292, "w": 184, "h": 256}, "spriteSourceSize": {"x": 0, "y": 0, "w": 256, "h": 184}, "sourceSize": {"w": 256, "h": 184}, "rotated": true, "offset": {"x": 0, "y": 0}}, "a1367646": {"frame": {"x": 1135, "y": 3098, "w": 181, "h": 256}, "spriteSourceSize": {"x": 0, "y": 0, "w": 256, "h": 181}, "sourceSize": {"w": 256, "h": 181}, "rotated": true, "offset": {"x": 0, "y": 0}}, "a1367647": {"frame": {"x": 403, "y": 1550, "w": 169, "h": 256}, "spriteSourceSize": {"x": 0, "y": 0, "w": 256, "h": 169}, "sourceSize": {"w": 256, "h": 169}, "rotated": true, "offset": {"x": 0, "y": 0}}, "a1367649": {"frame": {"x": 3850, "y": 1982, "w": 244, "h": 256}, "spriteSourceSize": {"x": 0, "y": 0, "w": 244, "h": 256}, "sourceSize": {"w": 244, "h": 256}, "rotated": false, "offset": {"x": 0, "y": 0}}, "a1367653": {"frame": {"x": 1451, "y": 2840, "w": 233, "h": 256}, "spriteSourceSize": {"x": 0, "y": 0, "w": 256, "h": 233}, "sourceSize": {"w": 256, "h": 233}, "rotated": true, "offset": {"x": 0, "y": 0}}, "a1367657": {"frame": {"x": 3579, "y": 260, "w": 169, "h": 256}, "spriteSourceSize": {"x": 0, "y": 0, "w": 256, "h": 169}, "sourceSize": {"w": 256, "h": 169}, "rotated": true, "offset": {"x": 0, "y": 0}}, "a1367659": {"frame": {"x": 318, "y": 3356, "w": 242, "h": 256}, "spriteSourceSize": {"x": 0, "y": 0, "w": 242, "h": 256}, "sourceSize": {"w": 242, "h": 256}, "rotated": false, "offset": {"x": 0, "y": 0}}, "a1367669": {"frame": {"x": 2637, "y": 518, "w": 187, "h": 256}, "spriteSourceSize": {"x": 0, "y": 0, "w": 187, "h": 256}, "sourceSize": {"w": 187, "h": 256}, "rotated": false, "offset": {"x": 0, "y": 0}}, "a1367670": {"frame": {"x": 3292, "y": 1034, "w": 199, "h": 256}, "spriteSourceSize": {"x": 0, "y": 0, "w": 256, "h": 199}, "sourceSize": {"w": 256, "h": 199}, "rotated": true, "offset": {"x": 0, "y": 0}}, "a1367676": {"frame": {"x": 1853, "y": 518, "w": 178, "h": 256}, "spriteSourceSize": {"x": 0, "y": 0, "w": 178, "h": 256}, "sourceSize": {"w": 178, "h": 256}, "rotated": false, "offset": {"x": 0, "y": 0}}, "a1367679": {"frame": {"x": 1452, "y": 776, "w": 218, "h": 256}, "spriteSourceSize": {"x": 0, "y": 0, "w": 256, "h": 218}, "sourceSize": {"w": 256, "h": 218}, "rotated": true, "offset": {"x": 0, "y": 0}}, "a1367689": {"frame": {"x": 1018, "y": 2324, "w": 172, "h": 256}, "spriteSourceSize": {"x": 0, "y": 0, "w": 256, "h": 172}, "sourceSize": {"w": 256, "h": 172}, "rotated": true, "offset": {"x": 0, "y": 0}}, "a1367691": {"frame": {"x": 925, "y": 1550, "w": 180, "h": 256}, "spriteSourceSize": {"x": 0, "y": 0, "w": 180, "h": 256}, "sourceSize": {"w": 180, "h": 256}, "rotated": false, "offset": {"x": 0, "y": 0}}, "a1367695": {"frame": {"x": 195, "y": 3614, "w": 164, "h": 256}, "spriteSourceSize": {"x": 0, "y": 0, "w": 256, "h": 164}, "sourceSize": {"w": 256, "h": 164}, "rotated": true, "offset": {"x": 0, "y": 0}}, "a1367699": {"frame": {"x": 2, "y": 2, "w": 227, "h": 256}, "spriteSourceSize": {"x": 0, "y": 0, "w": 256, "h": 227}, "sourceSize": {"w": 256, "h": 227}, "rotated": true, "offset": {"x": 0, "y": 0}}, "a1367706": {"frame": {"x": 1091, "y": 518, "w": 180, "h": 256}, "spriteSourceSize": {"x": 0, "y": 0, "w": 256, "h": 180}, "sourceSize": {"w": 256, "h": 180}, "rotated": true, "offset": {"x": 0, "y": 0}}, "a1367707": {"frame": {"x": 2, "y": 3872, "w": 256, "h": 186}, "spriteSourceSize": {"x": 0, "y": 0, "w": 256, "h": 186}, "sourceSize": {"w": 256, "h": 186}, "rotated": false, "offset": {"x": 0, "y": 0}}, "a1367714": {"frame": {"x": 508, "y": 518, "w": 190, "h": 256}, "spriteSourceSize": {"x": 0, "y": 0, "w": 256, "h": 190}, "sourceSize": {"w": 256, "h": 190}, "rotated": true, "offset": {"x": 0, "y": 0}}, "a2813003": {"frame": {"x": 2036, "y": 1550, "w": 176, "h": 256}, "spriteSourceSize": {"x": 0, "y": 0, "w": 176, "h": 256}, "sourceSize": {"w": 176, "h": 256}, "rotated": false, "offset": {"x": 0, "y": 0}}, "a2813010": {"frame": {"x": 577, "y": 3614, "w": 162, "h": 256}, "spriteSourceSize": {"x": 0, "y": 0, "w": 162, "h": 256}, "sourceSize": {"w": 162, "h": 256}, "rotated": false, "offset": {"x": 0, "y": 0}}, "a2813050": {"frame": {"x": 1258, "y": 3614, "w": 170, "h": 256}, "spriteSourceSize": {"x": 0, "y": 0, "w": 170, "h": 256}, "sourceSize": {"w": 170, "h": 256}, "rotated": false, "offset": {"x": 0, "y": 0}}, "a2813066": {"frame": {"x": 2305, "y": 2066, "w": 180, "h": 256}, "spriteSourceSize": {"x": 0, "y": 0, "w": 180, "h": 256}, "sourceSize": {"w": 180, "h": 256}, "rotated": false, "offset": {"x": 0, "y": 0}}, "a2813070": {"frame": {"x": 3557, "y": 2840, "w": 192, "h": 256}, "spriteSourceSize": {"x": 0, "y": 0, "w": 192, "h": 256}, "sourceSize": {"w": 192, "h": 256}, "rotated": false, "offset": {"x": 0, "y": 0}}, "a2813071": {"frame": {"x": 3811, "y": 195, "w": 256, "h": 192}, "spriteSourceSize": {"x": 0, "y": 0, "w": 192, "h": 256}, "sourceSize": {"w": 192, "h": 256}, "rotated": true, "offset": {"x": 0, "y": 0}}, "a2813072": {"frame": {"x": 379, "y": 2840, "w": 172, "h": 256}, "spriteSourceSize": {"x": 0, "y": 0, "w": 172, "h": 256}, "sourceSize": {"w": 172, "h": 256}, "rotated": false, "offset": {"x": 0, "y": 0}}, "a2813074": {"frame": {"x": 2, "y": 2582, "w": 164, "h": 256}, "spriteSourceSize": {"x": 0, "y": 0, "w": 164, "h": 256}, "sourceSize": {"w": 164, "h": 256}, "rotated": false, "offset": {"x": 0, "y": 0}}, "a5371001": {"frame": {"x": 148, "y": 3356, "w": 168, "h": 256}, "spriteSourceSize": {"x": 0, "y": 0, "w": 168, "h": 256}, "sourceSize": {"w": 168, "h": 256}, "rotated": false, "offset": {"x": 0, "y": 0}}, "a5371018": {"frame": {"x": 3014, "y": 1292, "w": 166, "h": 256}, "spriteSourceSize": {"x": 0, "y": 0, "w": 256, "h": 166}, "sourceSize": {"w": 256, "h": 166}, "rotated": true, "offset": {"x": 0, "y": 0}}, "a5371042": {"frame": {"x": 526, "y": 2324, "w": 173, "h": 256}, "spriteSourceSize": {"x": 0, "y": 0, "w": 173, "h": 256}, "sourceSize": {"w": 173, "h": 256}, "rotated": false, "offset": {"x": 0, "y": 0}}, "a5371047": {"frame": {"x": 3295, "y": 2582, "w": 172, "h": 256}, "spriteSourceSize": {"x": 0, "y": 0, "w": 172, "h": 256}, "sourceSize": {"w": 172, "h": 256}, "rotated": false, "offset": {"x": 0, "y": 0}}, "a5371051": {"frame": {"x": 1714, "y": 2066, "w": 202, "h": 256}, "spriteSourceSize": {"x": 0, "y": 0, "w": 256, "h": 202}, "sourceSize": {"w": 256, "h": 202}, "rotated": true, "offset": {"x": 0, "y": 0}}, "a5371055": {"frame": {"x": 2001, "y": 2, "w": 197, "h": 256}, "spriteSourceSize": {"x": 0, "y": 0, "w": 197, "h": 256}, "sourceSize": {"w": 197, "h": 256}, "rotated": false, "offset": {"x": 0, "y": 0}}, "a5371058": {"frame": {"x": 2453, "y": 1808, "w": 173, "h": 256}, "spriteSourceSize": {"x": 0, "y": 0, "w": 173, "h": 256}, "sourceSize": {"w": 173, "h": 256}, "rotated": false, "offset": {"x": 0, "y": 0}}, "a5371071": {"frame": {"x": 3925, "y": 3098, "w": 167, "h": 256}, "spriteSourceSize": {"x": 0, "y": 0, "w": 167, "h": 256}, "sourceSize": {"w": 167, "h": 256}, "rotated": false, "offset": {"x": 0, "y": 0}}, "a5371072": {"frame": {"x": 3830, "y": 1808, "w": 256, "h": 172}, "spriteSourceSize": {"x": 0, "y": 0, "w": 172, "h": 256}, "sourceSize": {"w": 172, "h": 256}, "rotated": true, "offset": {"x": 0, "y": 0}}, "a5371078": {"frame": {"x": 2177, "y": 2324, "w": 165, "h": 256}, "spriteSourceSize": {"x": 0, "y": 0, "w": 256, "h": 165}, "sourceSize": {"w": 256, "h": 165}, "rotated": true, "offset": {"x": 0, "y": 0}}, "a6883008": {"frame": {"x": 1293, "y": 2, "w": 164, "h": 256}, "spriteSourceSize": {"x": 0, "y": 0, "w": 164, "h": 256}, "sourceSize": {"w": 164, "h": 256}, "rotated": false, "offset": {"x": 0, "y": 0}}, "a6883017": {"frame": {"x": 567, "y": 3098, "w": 170, "h": 256}, "spriteSourceSize": {"x": 0, "y": 0, "w": 170, "h": 256}, "sourceSize": {"w": 170, "h": 256}, "rotated": false, "offset": {"x": 0, "y": 0}}, "a6883020": {"frame": {"x": 2570, "y": 1550, "w": 176, "h": 256}, "spriteSourceSize": {"x": 0, "y": 0, "w": 176, "h": 256}, "sourceSize": {"w": 176, "h": 256}, "rotated": false, "offset": {"x": 0, "y": 0}}, "a6883023": {"frame": {"x": 585, "y": 1808, "w": 192, "h": 256}, "spriteSourceSize": {"x": 0, "y": 0, "w": 256, "h": 192}, "sourceSize": {"w": 256, "h": 192}, "rotated": true, "offset": {"x": 0, "y": 0}}, "a6883034": {"frame": {"x": 3310, "y": 2, "w": 149, "h": 256}, "spriteSourceSize": {"x": 0, "y": 0, "w": 149, "h": 256}, "sourceSize": {"w": 149, "h": 256}, "rotated": false, "offset": {"x": 0, "y": 0}}, "a6883039": {"frame": {"x": 2568, "y": 3614, "w": 175, "h": 256}, "spriteSourceSize": {"x": 0, "y": 0, "w": 256, "h": 175}, "sourceSize": {"w": 256, "h": 175}, "rotated": true, "offset": {"x": 0, "y": 0}}, "a6883046": {"frame": {"x": 2252, "y": 1808, "w": 199, "h": 256}, "spriteSourceSize": {"x": 0, "y": 0, "w": 256, "h": 199}, "sourceSize": {"w": 256, "h": 199}, "rotated": true, "offset": {"x": 0, "y": 0}}, "a6883067": {"frame": {"x": 3386, "y": 518, "w": 235, "h": 256}, "spriteSourceSize": {"x": 0, "y": 0, "w": 256, "h": 235}, "sourceSize": {"w": 256, "h": 235}, "rotated": true, "offset": {"x": 0, "y": 0}}, "a6883177": {"frame": {"x": 2927, "y": 3356, "w": 165, "h": 256}, "spriteSourceSize": {"x": 0, "y": 0, "w": 165, "h": 256}, "sourceSize": {"w": 165, "h": 256}, "rotated": false, "offset": {"x": 0, "y": 0}}, "a6883181": {"frame": {"x": 1808, "y": 3872, "w": 256, "h": 221}, "spriteSourceSize": {"x": 0, "y": 0, "w": 221, "h": 256}, "sourceSize": {"w": 221, "h": 256}, "rotated": true, "offset": {"x": 0, "y": 0}}, "a9613016": {"frame": {"x": 1918, "y": 1292, "w": 166, "h": 256}, "spriteSourceSize": {"x": 0, "y": 0, "w": 166, "h": 256}, "sourceSize": {"w": 166, "h": 256}, "rotated": false, "offset": {"x": 0, "y": 0}}, "a9613020": {"frame": {"x": 2239, "y": 1292, "w": 204, "h": 256}, "spriteSourceSize": {"x": 0, "y": 0, "w": 204, "h": 256}, "sourceSize": {"w": 204, "h": 256}, "rotated": false, "offset": {"x": 0, "y": 0}}, "c010380004": {"frame": {"x": 3477, "y": 3356, "w": 201, "h": 256}, "spriteSourceSize": {"x": 0, "y": 0, "w": 201, "h": 256}, "sourceSize": {"w": 201, "h": 256}, "rotated": false, "offset": {"x": 0, "y": 0}}, "c010440001": {"frame": {"x": 2, "y": 1808, "w": 179, "h": 256}, "spriteSourceSize": {"x": 0, "y": 0, "w": 179, "h": 256}, "sourceSize": {"w": 179, "h": 256}, "rotated": false, "offset": {"x": 0, "y": 0}}, "c010440010": {"frame": {"x": 1285, "y": 776, "w": 165, "h": 256}, "spriteSourceSize": {"x": 0, "y": 0, "w": 165, "h": 256}, "sourceSize": {"w": 165, "h": 256}, "rotated": false, "offset": {"x": 0, "y": 0}}, "c010490005": {"frame": {"x": 896, "y": 260, "w": 204, "h": 256}, "spriteSourceSize": {"x": 0, "y": 0, "w": 256, "h": 204}, "sourceSize": {"w": 256, "h": 204}, "rotated": true, "offset": {"x": 0, "y": 0}}, "c010490021": {"frame": {"x": 741, "y": 3614, "w": 165, "h": 256}, "spriteSourceSize": {"x": 0, "y": 0, "w": 165, "h": 256}, "sourceSize": {"w": 165, "h": 256}, "rotated": false, "offset": {"x": 0, "y": 0}}, "c011580001": {"frame": {"x": 1300, "y": 2066, "w": 207, "h": 256}, "spriteSourceSize": {"x": 0, "y": 0, "w": 207, "h": 256}, "sourceSize": {"w": 207, "h": 256}, "rotated": false, "offset": {"x": 0, "y": 0}}, "c011580012": {"frame": {"x": 3751, "y": 2840, "w": 206, "h": 256}, "spriteSourceSize": {"x": 0, "y": 0, "w": 256, "h": 206}, "sourceSize": {"w": 256, "h": 206}, "rotated": true, "offset": {"x": 0, "y": 0}}, "c027300009": {"frame": {"x": 176, "y": 2840, "w": 201, "h": 256}, "spriteSourceSize": {"x": 0, "y": 0, "w": 201, "h": 256}, "sourceSize": {"w": 201, "h": 256}, "rotated": false, "offset": {"x": 0, "y": 0}}, "c027520001": {"frame": {"x": 1989, "y": 1034, "w": 202, "h": 256}, "spriteSourceSize": {"x": 0, "y": 0, "w": 256, "h": 202}, "sourceSize": {"w": 256, "h": 202}, "rotated": true, "offset": {"x": 0, "y": 0}}, "c027520002": {"frame": {"x": 1459, "y": 2, "w": 165, "h": 256}, "spriteSourceSize": {"x": 0, "y": 0, "w": 165, "h": 256}, "sourceSize": {"w": 165, "h": 256}, "rotated": false, "offset": {"x": 0, "y": 0}}, "c027640001": {"frame": {"x": 3811, "y": 2, "w": 256, "h": 191}, "spriteSourceSize": {"x": 0, "y": 0, "w": 191, "h": 256}, "sourceSize": {"w": 191, "h": 256}, "rotated": true, "offset": {"x": 0, "y": 0}}, "c027640017": {"frame": {"x": 3125, "y": 1034, "w": 165, "h": 256}, "spriteSourceSize": {"x": 0, "y": 0, "w": 165, "h": 256}, "sourceSize": {"w": 165, "h": 256}, "rotated": false, "offset": {"x": 0, "y": 0}}, "c027640025": {"frame": {"x": 362, "y": 2582, "w": 200, "h": 256}, "spriteSourceSize": {"x": 0, "y": 0, "w": 256, "h": 200}, "sourceSize": {"w": 256, "h": 200}, "rotated": true, "offset": {"x": 0, "y": 0}}, "c027720043": {"frame": {"x": 3314, "y": 1808, "w": 171, "h": 256}, "spriteSourceSize": {"x": 0, "y": 0, "w": 171, "h": 256}, "sourceSize": {"w": 171, "h": 256}, "rotated": false, "offset": {"x": 0, "y": 0}}, "c027720050": {"frame": {"x": 3862, "y": 905, "w": 171, "h": 256}, "spriteSourceSize": {"x": 0, "y": 0, "w": 171, "h": 256}, "sourceSize": {"w": 171, "h": 256}, "rotated": false, "offset": {"x": 0, "y": 0}}, "c028140002": {"frame": {"x": 183, "y": 2324, "w": 193, "h": 256}, "spriteSourceSize": {"x": 0, "y": 0, "w": 193, "h": 256}, "sourceSize": {"w": 193, "h": 256}, "rotated": false, "offset": {"x": 0, "y": 0}}, "c028140003": {"frame": {"x": 917, "y": 518, "w": 172, "h": 256}, "spriteSourceSize": {"x": 0, "y": 0, "w": 172, "h": 256}, "sourceSize": {"w": 172, "h": 256}, "rotated": false, "offset": {"x": 0, "y": 0}}, "c028140014": {"frame": {"x": 701, "y": 2324, "w": 165, "h": 256}, "spriteSourceSize": {"x": 0, "y": 0, "w": 165, "h": 256}, "sourceSize": {"w": 165, "h": 256}, "rotated": false, "offset": {"x": 0, "y": 0}}, "c028140047": {"frame": {"x": 1100, "y": 2, "w": 191, "h": 256}, "spriteSourceSize": {"x": 0, "y": 0, "w": 191, "h": 256}, "sourceSize": {"w": 191, "h": 256}, "rotated": false, "offset": {"x": 0, "y": 0}}, "c028140056": {"frame": {"x": 2599, "y": 2, "w": 161, "h": 256}, "spriteSourceSize": {"x": 0, "y": 0, "w": 256, "h": 161}, "sourceSize": {"w": 256, "h": 161}, "rotated": true, "offset": {"x": 0, "y": 0}}, "c028610006": {"frame": {"x": 1061, "y": 2840, "w": 195, "h": 256}, "spriteSourceSize": {"x": 0, "y": 0, "w": 195, "h": 256}, "sourceSize": {"w": 195, "h": 256}, "rotated": false, "offset": {"x": 0, "y": 0}}, "c028610009": {"frame": {"x": 747, "y": 1550, "w": 176, "h": 256}, "spriteSourceSize": {"x": 0, "y": 0, "w": 176, "h": 256}, "sourceSize": {"w": 176, "h": 256}, "rotated": false, "offset": {"x": 0, "y": 0}}, "c028610019": {"frame": {"x": 1702, "y": 1808, "w": 172, "h": 256}, "spriteSourceSize": {"x": 0, "y": 0, "w": 256, "h": 172}, "sourceSize": {"w": 256, "h": 172}, "rotated": true, "offset": {"x": 0, "y": 0}}, "c028610024": {"frame": {"x": 3668, "y": 2324, "w": 196, "h": 256}, "spriteSourceSize": {"x": 0, "y": 0, "w": 196, "h": 256}, "sourceSize": {"w": 196, "h": 256}, "rotated": false, "offset": {"x": 0, "y": 0}}, "c028640004": {"frame": {"x": 2826, "y": 518, "w": 172, "h": 256}, "spriteSourceSize": {"x": 0, "y": 0, "w": 172, "h": 256}, "sourceSize": {"w": 172, "h": 256}, "rotated": false, "offset": {"x": 0, "y": 0}}, "c028640006": {"frame": {"x": 937, "y": 2066, "w": 192, "h": 256}, "spriteSourceSize": {"x": 0, "y": 0, "w": 192, "h": 256}, "sourceSize": {"w": 192, "h": 256}, "rotated": false, "offset": {"x": 0, "y": 0}}, "c028640007": {"frame": {"x": 1273, "y": 518, "w": 215, "h": 256}, "spriteSourceSize": {"x": 0, "y": 0, "w": 256, "h": 215}, "sourceSize": {"w": 256, "h": 215}, "rotated": true, "offset": {"x": 0, "y": 0}}, "c028640008": {"frame": {"x": 1592, "y": 2324, "w": 189, "h": 256}, "spriteSourceSize": {"x": 0, "y": 0, "w": 256, "h": 189}, "sourceSize": {"w": 256, "h": 189}, "rotated": true, "offset": {"x": 0, "y": 0}}, "c028640014": {"frame": {"x": 2, "y": 2066, "w": 172, "h": 256}, "spriteSourceSize": {"x": 0, "y": 0, "w": 172, "h": 256}, "sourceSize": {"w": 172, "h": 256}, "rotated": false, "offset": {"x": 0, "y": 0}}, "c028640015": {"frame": {"x": 1614, "y": 1034, "w": 170, "h": 256}, "spriteSourceSize": {"x": 0, "y": 0, "w": 170, "h": 256}, "sourceSize": {"w": 170, "h": 256}, "rotated": false, "offset": {"x": 0, "y": 0}}, "c028640050": {"frame": {"x": 2428, "y": 518, "w": 207, "h": 256}, "spriteSourceSize": {"x": 0, "y": 0, "w": 207, "h": 256}, "sourceSize": {"w": 207, "h": 256}, "rotated": false, "offset": {"x": 0, "y": 0}}, "c028640051": {"frame": {"x": 384, "y": 1292, "w": 154, "h": 256}, "spriteSourceSize": {"x": 0, "y": 0, "w": 154, "h": 256}, "sourceSize": {"w": 154, "h": 256}, "rotated": false, "offset": {"x": 0, "y": 0}}, "c028640063": {"frame": {"x": 333, "y": 1034, "w": 217, "h": 256}, "spriteSourceSize": {"x": 0, "y": 0, "w": 217, "h": 256}, "sourceSize": {"w": 217, "h": 256}, "rotated": false, "offset": {"x": 0, "y": 0}}, "c029490018": {"frame": {"x": 3094, "y": 3356, "w": 201, "h": 256}, "spriteSourceSize": {"x": 0, "y": 0, "w": 201, "h": 256}, "sourceSize": {"w": 201, "h": 256}, "rotated": false, "offset": {"x": 0, "y": 0}}, "c029490072": {"frame": {"x": 178, "y": 776, "w": 164, "h": 256}, "spriteSourceSize": {"x": 0, "y": 0, "w": 164, "h": 256}, "sourceSize": {"w": 164, "h": 256}, "rotated": false, "offset": {"x": 0, "y": 0}}, "c029500006": {"frame": {"x": 3510, "y": 1550, "w": 151, "h": 256}, "spriteSourceSize": {"x": 0, "y": 0, "w": 151, "h": 256}, "sourceSize": {"w": 151, "h": 256}, "rotated": false, "offset": {"x": 0, "y": 0}}, "c029510001": {"frame": {"x": 2893, "y": 2324, "w": 169, "h": 256}, "spriteSourceSize": {"x": 0, "y": 0, "w": 169, "h": 256}, "sourceSize": {"w": 169, "h": 256}, "rotated": false, "offset": {"x": 0, "y": 0}}, "c029510017": {"frame": {"x": 2745, "y": 3614, "w": 153, "h": 256}, "spriteSourceSize": {"x": 0, "y": 0, "w": 153, "h": 256}, "sourceSize": {"w": 153, "h": 256}, "rotated": false, "offset": {"x": 0, "y": 0}}, "c029520008": {"frame": {"x": 3200, "y": 2840, "w": 162, "h": 256}, "spriteSourceSize": {"x": 0, "y": 0, "w": 256, "h": 162}, "sourceSize": {"w": 256, "h": 162}, "rotated": true, "offset": {"x": 0, "y": 0}}, "c031660001": {"frame": {"x": 2737, "y": 1034, "w": 198, "h": 256}, "spriteSourceSize": {"x": 0, "y": 0, "w": 198, "h": 256}, "sourceSize": {"w": 198, "h": 256}, "rotated": false, "offset": {"x": 0, "y": 0}}, "c032530007": {"frame": {"x": 3107, "y": 1808, "w": 205, "h": 256}, "spriteSourceSize": {"x": 0, "y": 0, "w": 205, "h": 256}, "sourceSize": {"w": 205, "h": 256}, "rotated": false, "offset": {"x": 0, "y": 0}}, "c032530009": {"frame": {"x": 3637, "y": 2, "w": 172, "h": 256}, "spriteSourceSize": {"x": 0, "y": 0, "w": 172, "h": 256}, "sourceSize": {"w": 172, "h": 256}, "rotated": false, "offset": {"x": 0, "y": 0}}, "c032560015": {"frame": {"x": 2, "y": 1550, "w": 180, "h": 256}, "spriteSourceSize": {"x": 0, "y": 0, "w": 256, "h": 180}, "sourceSize": {"w": 256, "h": 180}, "rotated": true, "offset": {"x": 0, "y": 0}}, "c032560020": {"frame": {"x": 1777, "y": 3614, "w": 212, "h": 256}, "spriteSourceSize": {"x": 0, "y": 0, "w": 212, "h": 256}, "sourceSize": {"w": 212, "h": 256}, "rotated": false, "offset": {"x": 0, "y": 0}}, "c032560047": {"frame": {"x": 175, "y": 1292, "w": 207, "h": 256}, "spriteSourceSize": {"x": 0, "y": 0, "w": 207, "h": 256}, "sourceSize": {"w": 207, "h": 256}, "rotated": false, "offset": {"x": 0, "y": 0}}, "c032560048": {"frame": {"x": 779, "y": 1808, "w": 162, "h": 256}, "spriteSourceSize": {"x": 0, "y": 0, "w": 162, "h": 256}, "sourceSize": {"w": 162, "h": 256}, "rotated": false, "offset": {"x": 0, "y": 0}}, "c032720009": {"frame": {"x": 1130, "y": 1292, "w": 206, "h": 256}, "spriteSourceSize": {"x": 0, "y": 0, "w": 256, "h": 206}, "sourceSize": {"w": 256, "h": 206}, "rotated": true, "offset": {"x": 0, "y": 0}}, "c032720016": {"frame": {"x": 187, "y": 1034, "w": 144, "h": 256}, "spriteSourceSize": {"x": 0, "y": 0, "w": 256, "h": 144}, "sourceSize": {"w": 256, "h": 144}, "rotated": true, "offset": {"x": 0, "y": 0}}, "c032720019": {"frame": {"x": 1686, "y": 2840, "w": 178, "h": 256}, "spriteSourceSize": {"x": 0, "y": 0, "w": 178, "h": 256}, "sourceSize": {"w": 178, "h": 256}, "rotated": false, "offset": {"x": 0, "y": 0}}, "c032730003": {"frame": {"x": 3682, "y": 2066, "w": 166, "h": 256}, "spriteSourceSize": {"x": 0, "y": 0, "w": 166, "h": 256}, "sourceSize": {"w": 166, "h": 256}, "rotated": false, "offset": {"x": 0, "y": 0}}, "c032730004": {"frame": {"x": 2398, "y": 1550, "w": 170, "h": 256}, "spriteSourceSize": {"x": 0, "y": 0, "w": 256, "h": 170}, "sourceSize": {"w": 256, "h": 170}, "rotated": true, "offset": {"x": 0, "y": 0}}, "c032740001": {"frame": {"x": 2147, "y": 2582, "w": 205, "h": 256}, "spriteSourceSize": {"x": 0, "y": 0, "w": 205, "h": 256}, "sourceSize": {"w": 205, "h": 256}, "rotated": false, "offset": {"x": 0, "y": 0}}, "c032740003": {"frame": {"x": 1338, "y": 1292, "w": 160, "h": 256}, "spriteSourceSize": {"x": 0, "y": 0, "w": 256, "h": 160}, "sourceSize": {"w": 256, "h": 160}, "rotated": true, "offset": {"x": 0, "y": 0}}, "c032740005": {"frame": {"x": 1854, "y": 260, "w": 161, "h": 256}, "spriteSourceSize": {"x": 0, "y": 0, "w": 161, "h": 256}, "sourceSize": {"w": 161, "h": 256}, "rotated": false, "offset": {"x": 0, "y": 0}}, "c032740019": {"frame": {"x": 2042, "y": 776, "w": 172, "h": 256}, "spriteSourceSize": {"x": 0, "y": 0, "w": 172, "h": 256}, "sourceSize": {"w": 172, "h": 256}, "rotated": false, "offset": {"x": 0, "y": 0}}, "c032740021": {"frame": {"x": 2, "y": 776, "w": 174, "h": 256}, "spriteSourceSize": {"x": 0, "y": 0, "w": 174, "h": 256}, "sourceSize": {"w": 174, "h": 256}, "rotated": false, "offset": {"x": 0, "y": 0}}, "c032740042": {"frame": {"x": 564, "y": 2582, "w": 205, "h": 256}, "spriteSourceSize": {"x": 0, "y": 0, "w": 205, "h": 256}, "sourceSize": {"w": 205, "h": 256}, "rotated": false, "offset": {"x": 0, "y": 0}}, "c032750007": {"frame": {"x": 3554, "y": 3098, "w": 170, "h": 256}, "spriteSourceSize": {"x": 0, "y": 0, "w": 256, "h": 170}, "sourceSize": {"w": 256, "h": 170}, "rotated": true, "offset": {"x": 0, "y": 0}}, "c032750010": {"frame": {"x": 2, "y": 3614, "w": 191, "h": 256}, "spriteSourceSize": {"x": 0, "y": 0, "w": 191, "h": 256}, "sourceSize": {"w": 191, "h": 256}, "rotated": false, "offset": {"x": 0, "y": 0}}, "c032750025": {"frame": {"x": 941, "y": 3356, "w": 165, "h": 256}, "spriteSourceSize": {"x": 0, "y": 0, "w": 256, "h": 165}, "sourceSize": {"w": 256, "h": 165}, "rotated": true, "offset": {"x": 0, "y": 0}}, "c032770010": {"frame": {"x": 3540, "y": 776, "w": 166, "h": 256}, "spriteSourceSize": {"x": 0, "y": 0, "w": 166, "h": 256}, "sourceSize": {"w": 166, "h": 256}, "rotated": false, "offset": {"x": 0, "y": 0}}, "c032770020": {"frame": {"x": 1509, "y": 2066, "w": 203, "h": 256}, "spriteSourceSize": {"x": 0, "y": 0, "w": 256, "h": 203}, "sourceSize": {"w": 256, "h": 203}, "rotated": true, "offset": {"x": 0, "y": 0}}, "c032770026": {"frame": {"x": 183, "y": 1808, "w": 238, "h": 256}, "spriteSourceSize": {"x": 0, "y": 0, "w": 238, "h": 256}, "sourceSize": {"w": 238, "h": 256}, "rotated": false, "offset": {"x": 0, "y": 0}}, "c032770032": {"frame": {"x": 3389, "y": 260, "w": 188, "h": 256}, "spriteSourceSize": {"x": 0, "y": 0, "w": 188, "h": 256}, "sourceSize": {"w": 188, "h": 256}, "rotated": false, "offset": {"x": 0, "y": 0}}, "c032770040": {"frame": {"x": 3049, "y": 2066, "w": 199, "h": 256}, "spriteSourceSize": {"x": 0, "y": 0, "w": 256, "h": 199}, "sourceSize": {"w": 256, "h": 199}, "rotated": true, "offset": {"x": 0, "y": 0}}, "c032770055": {"frame": {"x": 3000, "y": 518, "w": 165, "h": 256}, "spriteSourceSize": {"x": 0, "y": 0, "w": 165, "h": 256}, "sourceSize": {"w": 165, "h": 256}, "rotated": false, "offset": {"x": 0, "y": 0}}, "c032770064": {"frame": {"x": 176, "y": 2066, "w": 166, "h": 256}, "spriteSourceSize": {"x": 0, "y": 0, "w": 166, "h": 256}, "sourceSize": {"w": 166, "h": 256}, "rotated": false, "offset": {"x": 0, "y": 0}}, "c032770073": {"frame": {"x": 2942, "y": 2, "w": 163, "h": 256}, "spriteSourceSize": {"x": 0, "y": 0, "w": 163, "h": 256}, "sourceSize": {"w": 163, "h": 256}, "rotated": false, "offset": {"x": 0, "y": 0}}, "c032770077": {"frame": {"x": 2900, "y": 3614, "w": 184, "h": 256}, "spriteSourceSize": {"x": 0, "y": 0, "w": 184, "h": 256}, "sourceSize": {"w": 184, "h": 256}, "rotated": false, "offset": {"x": 0, "y": 0}}, "c032770088": {"frame": {"x": 2731, "y": 2324, "w": 160, "h": 256}, "spriteSourceSize": {"x": 0, "y": 0, "w": 256, "h": 160}, "sourceSize": {"w": 256, "h": 160}, "rotated": true, "offset": {"x": 0, "y": 0}}, "c032790005": {"frame": {"x": 2263, "y": 3098, "w": 165, "h": 256}, "spriteSourceSize": {"x": 0, "y": 0, "w": 165, "h": 256}, "sourceSize": {"w": 165, "h": 256}, "rotated": false, "offset": {"x": 0, "y": 0}}, "c032790027": {"frame": {"x": 1192, "y": 2324, "w": 210, "h": 256}, "spriteSourceSize": {"x": 0, "y": 0, "w": 210, "h": 256}, "sourceSize": {"w": 210, "h": 256}, "rotated": false, "offset": {"x": 0, "y": 0}}, "c032790028": {"frame": {"x": 1131, "y": 2066, "w": 167, "h": 256}, "spriteSourceSize": {"x": 0, "y": 0, "w": 167, "h": 256}, "sourceSize": {"w": 167, "h": 256}, "rotated": false, "offset": {"x": 0, "y": 0}}, "c032790030": {"frame": {"x": 518, "y": 3872, "w": 256, "h": 166}, "spriteSourceSize": {"x": 0, "y": 0, "w": 256, "h": 166}, "sourceSize": {"w": 256, "h": 166}, "rotated": false, "offset": {"x": 0, "y": 0}}, "c032790034": {"frame": {"x": 908, "y": 3614, "w": 202, "h": 256}, "spriteSourceSize": {"x": 0, "y": 0, "w": 202, "h": 256}, "sourceSize": {"w": 202, "h": 256}, "rotated": false, "offset": {"x": 0, "y": 0}}, "c032790063": {"frame": {"x": 1492, "y": 1550, "w": 171, "h": 256}, "spriteSourceSize": {"x": 0, "y": 0, "w": 256, "h": 171}, "sourceSize": {"w": 256, "h": 171}, "rotated": true, "offset": {"x": 0, "y": 0}}, "c032800005": {"frame": {"x": 2365, "y": 3614, "w": 201, "h": 256}, "spriteSourceSize": {"x": 0, "y": 0, "w": 201, "h": 256}, "sourceSize": {"w": 201, "h": 256}, "rotated": false, "offset": {"x": 0, "y": 0}}, "c032800013": {"frame": {"x": 1285, "y": 3356, "w": 185, "h": 256}, "spriteSourceSize": {"x": 0, "y": 0, "w": 185, "h": 256}, "sourceSize": {"w": 185, "h": 256}, "rotated": false, "offset": {"x": 0, "y": 0}}, "c032800019": {"frame": {"x": 1665, "y": 518, "w": 186, "h": 256}, "spriteSourceSize": {"x": 0, "y": 0, "w": 256, "h": 186}, "sourceSize": {"w": 256, "h": 186}, "rotated": true, "offset": {"x": 0, "y": 0}}, "c032800020": {"frame": {"x": 334, "y": 518, "w": 172, "h": 256}, "spriteSourceSize": {"x": 0, "y": 0, "w": 172, "h": 256}, "sourceSize": {"w": 172, "h": 256}, "rotated": false, "offset": {"x": 0, "y": 0}}, "c032800021": {"frame": {"x": 3614, "y": 3872, "w": 256, "h": 162}, "spriteSourceSize": {"x": 0, "y": 0, "w": 162, "h": 256}, "sourceSize": {"w": 162, "h": 256}, "rotated": true, "offset": {"x": 0, "y": 0}}, "c032800042": {"frame": {"x": 2585, "y": 3098, "w": 172, "h": 256}, "spriteSourceSize": {"x": 0, "y": 0, "w": 172, "h": 256}, "sourceSize": {"w": 172, "h": 256}, "rotated": false, "offset": {"x": 0, "y": 0}}, "c032800065": {"frame": {"x": 214, "y": 3098, "w": 171, "h": 256}, "spriteSourceSize": {"x": 0, "y": 0, "w": 171, "h": 256}, "sourceSize": {"w": 171, "h": 256}, "rotated": false, "offset": {"x": 0, "y": 0}}, "c032800073": {"frame": {"x": 1528, "y": 3098, "w": 168, "h": 256}, "spriteSourceSize": {"x": 0, "y": 0, "w": 168, "h": 256}, "sourceSize": {"w": 168, "h": 256}, "rotated": false, "offset": {"x": 0, "y": 0}}, "c032810004": {"frame": {"x": 1430, "y": 3614, "w": 175, "h": 256}, "spriteSourceSize": {"x": 0, "y": 0, "w": 175, "h": 256}, "sourceSize": {"w": 175, "h": 256}, "rotated": false, "offset": {"x": 0, "y": 0}}, "c032810007": {"frame": {"x": 726, "y": 1292, "w": 208, "h": 256}, "spriteSourceSize": {"x": 0, "y": 0, "w": 256, "h": 208}, "sourceSize": {"w": 256, "h": 208}, "rotated": true, "offset": {"x": 0, "y": 0}}, "c032810015": {"frame": {"x": 3866, "y": 2240, "w": 176, "h": 256}, "spriteSourceSize": {"x": 0, "y": 0, "w": 176, "h": 256}, "sourceSize": {"w": 176, "h": 256}, "rotated": false, "offset": {"x": 0, "y": 0}}, "c032860002": {"frame": {"x": 3845, "y": 1550, "w": 176, "h": 256}, "spriteSourceSize": {"x": 0, "y": 0, "w": 176, "h": 256}, "sourceSize": {"w": 176, "h": 256}, "rotated": false, "offset": {"x": 0, "y": 0}}, "c032920005": {"frame": {"x": 2588, "y": 3356, "w": 161, "h": 256}, "spriteSourceSize": {"x": 0, "y": 0, "w": 256, "h": 161}, "sourceSize": {"w": 256, "h": 161}, "rotated": true, "offset": {"x": 0, "y": 0}}, "c032920021": {"frame": {"x": 3461, "y": 2, "w": 174, "h": 256}, "spriteSourceSize": {"x": 0, "y": 0, "w": 256, "h": 174}, "sourceSize": {"w": 256, "h": 174}, "rotated": true, "offset": {"x": 0, "y": 0}}, "c032920044": {"frame": {"x": 2324, "y": 3872, "w": 256, "h": 192}, "spriteSourceSize": {"x": 0, "y": 0, "w": 192, "h": 256}, "sourceSize": {"w": 192, "h": 256}, "rotated": true, "offset": {"x": 0, "y": 0}}, "c032920046": {"frame": {"x": 186, "y": 260, "w": 172, "h": 256}, "spriteSourceSize": {"x": 0, "y": 0, "w": 172, "h": 256}, "sourceSize": {"w": 172, "h": 256}, "rotated": false, "offset": {"x": 0, "y": 0}}, "c033570021": {"frame": {"x": 2751, "y": 3356, "w": 174, "h": 256}, "spriteSourceSize": {"x": 0, "y": 0, "w": 174, "h": 256}, "sourceSize": {"w": 174, "h": 256}, "rotated": false, "offset": {"x": 0, "y": 0}}, "c033570040": {"frame": {"x": 1115, "y": 776, "w": 168, "h": 256}, "spriteSourceSize": {"x": 0, "y": 0, "w": 168, "h": 256}, "sourceSize": {"w": 168, "h": 256}, "rotated": false, "offset": {"x": 0, "y": 0}}, "c033570062": {"frame": {"x": 1786, "y": 1034, "w": 201, "h": 256}, "spriteSourceSize": {"x": 0, "y": 0, "w": 201, "h": 256}, "sourceSize": {"w": 201, "h": 256}, "rotated": false, "offset": {"x": 0, "y": 0}}, "c033570063": {"frame": {"x": 2759, "y": 3098, "w": 205, "h": 256}, "spriteSourceSize": {"x": 0, "y": 0, "w": 205, "h": 256}, "sourceSize": {"w": 205, "h": 256}, "rotated": false, "offset": {"x": 0, "y": 0}}, "c033580001": {"frame": {"x": 2433, "y": 2840, "w": 182, "h": 256}, "spriteSourceSize": {"x": 0, "y": 0, "w": 182, "h": 256}, "sourceSize": {"w": 182, "h": 256}, "rotated": false, "offset": {"x": 0, "y": 0}}, "c033580009": {"frame": {"x": 3365, "y": 776, "w": 173, "h": 256}, "spriteSourceSize": {"x": 0, "y": 0, "w": 173, "h": 256}, "sourceSize": {"w": 173, "h": 256}, "rotated": false, "offset": {"x": 0, "y": 0}}, "c033580013": {"frame": {"x": 231, "y": 2, "w": 171, "h": 256}, "spriteSourceSize": {"x": 0, "y": 0, "w": 256, "h": 171}, "sourceSize": {"w": 256, "h": 171}, "rotated": true, "offset": {"x": 0, "y": 0}}, "c035520016": {"frame": {"x": 3866, "y": 2498, "w": 174, "h": 256}, "spriteSourceSize": {"x": 0, "y": 0, "w": 174, "h": 256}, "sourceSize": {"w": 174, "h": 256}, "rotated": false, "offset": {"x": 0, "y": 0}}, "c035520035": {"frame": {"x": 2426, "y": 776, "w": 219, "h": 256}, "spriteSourceSize": {"x": 0, "y": 0, "w": 219, "h": 256}, "sourceSize": {"w": 219, "h": 256}, "rotated": false, "offset": {"x": 0, "y": 0}}, "c035620011": {"frame": {"x": 574, "y": 1550, "w": 171, "h": 256}, "spriteSourceSize": {"x": 0, "y": 0, "w": 256, "h": 171}, "sourceSize": {"w": 256, "h": 171}, "rotated": true, "offset": {"x": 0, "y": 0}}, "c035620019": {"frame": {"x": 1437, "y": 1034, "w": 175, "h": 256}, "spriteSourceSize": {"x": 0, "y": 0, "w": 175, "h": 256}, "sourceSize": {"w": 175, "h": 256}, "rotated": false, "offset": {"x": 0, "y": 0}}, "c035620020": {"frame": {"x": 2808, "y": 776, "w": 204, "h": 256}, "spriteSourceSize": {"x": 0, "y": 0, "w": 204, "h": 256}, "sourceSize": {"w": 204, "h": 256}, "rotated": false, "offset": {"x": 0, "y": 0}}, "c035650002": {"frame": {"x": 1665, "y": 1550, "w": 194, "h": 256}, "spriteSourceSize": {"x": 0, "y": 0, "w": 194, "h": 256}, "sourceSize": {"w": 194, "h": 256}, "rotated": false, "offset": {"x": 0, "y": 0}}, "c035650003": {"frame": {"x": 3679, "y": 3614, "w": 163, "h": 256}, "spriteSourceSize": {"x": 0, "y": 0, "w": 163, "h": 256}, "sourceSize": {"w": 163, "h": 256}, "rotated": false, "offset": {"x": 0, "y": 0}}, "c035650015": {"frame": {"x": 2017, "y": 260, "w": 204, "h": 256}, "spriteSourceSize": {"x": 0, "y": 0, "w": 204, "h": 256}, "sourceSize": {"w": 204, "h": 256}, "rotated": false, "offset": {"x": 0, "y": 0}}, "c035650019": {"frame": {"x": 2630, "y": 260, "w": 163, "h": 256}, "spriteSourceSize": {"x": 0, "y": 0, "w": 256, "h": 163}, "sourceSize": {"w": 256, "h": 163}, "rotated": true, "offset": {"x": 0, "y": 0}}, "c035650036": {"frame": {"x": 2201, "y": 3356, "w": 207, "h": 256}, "spriteSourceSize": {"x": 0, "y": 0, "w": 207, "h": 256}, "sourceSize": {"w": 207, "h": 256}, "rotated": false, "offset": {"x": 0, "y": 0}}, "c035650039": {"frame": {"x": 1607, "y": 3614, "w": 168, "h": 256}, "spriteSourceSize": {"x": 0, "y": 0, "w": 168, "h": 256}, "sourceSize": {"w": 168, "h": 256}, "rotated": false, "offset": {"x": 0, "y": 0}}, "c035650052": {"frame": {"x": 3420, "y": 2324, "w": 246, "h": 256}, "spriteSourceSize": {"x": 0, "y": 0, "w": 246, "h": 256}, "sourceSize": {"w": 246, "h": 256}, "rotated": false, "offset": {"x": 0, "y": 0}}, "c035660002": {"frame": {"x": 2748, "y": 1550, "w": 196, "h": 256}, "spriteSourceSize": {"x": 0, "y": 0, "w": 196, "h": 256}, "sourceSize": {"w": 196, "h": 256}, "rotated": false, "offset": {"x": 0, "y": 0}}, "c035660005": {"frame": {"x": 3676, "y": 2582, "w": 173, "h": 256}, "spriteSourceSize": {"x": 0, "y": 0, "w": 173, "h": 256}, "sourceSize": {"w": 173, "h": 256}, "rotated": false, "offset": {"x": 0, "y": 0}}, "c035660015": {"frame": {"x": 1876, "y": 1808, "w": 197, "h": 256}, "spriteSourceSize": {"x": 0, "y": 0, "w": 197, "h": 256}, "sourceSize": {"w": 197, "h": 256}, "rotated": false, "offset": {"x": 0, "y": 0}}, "c035670010": {"frame": {"x": 3014, "y": 776, "w": 168, "h": 256}, "spriteSourceSize": {"x": 0, "y": 0, "w": 168, "h": 256}, "sourceSize": {"w": 168, "h": 256}, "rotated": false, "offset": {"x": 0, "y": 0}}, "c035670016": {"frame": {"x": 932, "y": 2, "w": 166, "h": 256}, "spriteSourceSize": {"x": 0, "y": 0, "w": 166, "h": 256}, "sourceSize": {"w": 166, "h": 256}, "rotated": false, "offset": {"x": 0, "y": 0}}, "c035670027": {"frame": {"x": 3459, "y": 3614, "w": 218, "h": 256}, "spriteSourceSize": {"x": 0, "y": 0, "w": 218, "h": 256}, "sourceSize": {"w": 218, "h": 256}, "rotated": false, "offset": {"x": 0, "y": 0}}, "c035670044": {"frame": {"x": 2946, "y": 1550, "w": 174, "h": 256}, "spriteSourceSize": {"x": 0, "y": 0, "w": 174, "h": 256}, "sourceSize": {"w": 174, "h": 256}, "rotated": false, "offset": {"x": 0, "y": 0}}, "c035670047": {"frame": {"x": 1654, "y": 260, "w": 198, "h": 256}, "spriteSourceSize": {"x": 0, "y": 0, "w": 256, "h": 198}, "sourceSize": {"w": 256, "h": 198}, "rotated": true, "offset": {"x": 0, "y": 0}}, "c035690005": {"frame": {"x": 2735, "y": 2582, "w": 171, "h": 256}, "spriteSourceSize": {"x": 0, "y": 0, "w": 256, "h": 171}, "sourceSize": {"w": 256, "h": 171}, "rotated": true, "offset": {"x": 0, "y": 0}}, "c035690006": {"frame": {"x": 1318, "y": 3098, "w": 208, "h": 256}, "spriteSourceSize": {"x": 0, "y": 0, "w": 208, "h": 256}, "sourceSize": {"w": 208, "h": 256}, "rotated": false, "offset": {"x": 0, "y": 0}}, "c041070022": {"frame": {"x": 3623, "y": 518, "w": 161, "h": 256}, "spriteSourceSize": {"x": 0, "y": 0, "w": 256, "h": 161}, "sourceSize": {"w": 256, "h": 161}, "rotated": true, "offset": {"x": 0, "y": 0}}, "c041070045": {"frame": {"x": 2193, "y": 1034, "w": 174, "h": 256}, "spriteSourceSize": {"x": 0, "y": 0, "w": 174, "h": 256}, "sourceSize": {"w": 174, "h": 256}, "rotated": false, "offset": {"x": 0, "y": 0}}, "c041280001": {"frame": {"x": 1322, "y": 1550, "w": 168, "h": 256}, "spriteSourceSize": {"x": 0, "y": 0, "w": 168, "h": 256}, "sourceSize": {"w": 168, "h": 256}, "rotated": false, "offset": {"x": 0, "y": 0}}}, "filename": "subdivisions_0.png"}